pyftt/__init__.py
pyftt/pyftt.py
pyftt-0.0.1.dist-info/LICENSE
pyftt-0.0.1.dist-info/METADATA
pyftt-0.0.1.dist-info/WHEEL
pyftt-0.0.1.dist-info/top_level.txt
pyftt-0.0.1.dist-info/RECORD
