Metadata-Version: 2.1
Name: pyftt
Version: 0.0.1
Summary: sparse-array partial tracing
Home-page: UNKNOWN
Author: Julio Candanedo
Author-email: juliojcandanedo@gmail.com
License: MIT
Platform: UNKNOWN
Classifier: Operating System :: OS Independent
Classifier: License :: OSI Approved :: MIT License
Classifier: Programming Language :: Python :: 3
Requires-Dist: numpy
